{"/":{"bundle.f9bc4.css":{"type":"style","weight":1},"bundle.a8314.esm.js":{"type":"script","weight":1}},"/about":{"bundle.f9bc4.css":{"type":"style","weight":1},"bundle.a8314.esm.js":{"type":"script","weight":1},"route-about.chunk.d5460.esm.js":{"type":"script","weight":0.9},"route-about.chunk.3ba37.css":{"type":"style","weight":0.9}},"/blog-detail":{"bundle.f9bc4.css":{"type":"style","weight":1},"bundle.a8314.esm.js":{"type":"script","weight":1},"route-blog-detail.chunk.dcf62.esm.js":{"type":"script","weight":0.9},"route-blog-detail.chunk.f4d7f.css":{"type":"style","weight":0.9}},"/blog-list":{"bundle.f9bc4.css":{"type":"style","weight":1},"bundle.a8314.esm.js":{"type":"script","weight":1},"route-blog-list.chunk.069ca.esm.js":{"type":"script","weight":0.9},"route-blog-list.chunk.2d227.css":{"type":"style","weight":0.9}},"/tags":{"bundle.f9bc4.css":{"type":"style","weight":1},"bundle.a8314.esm.js":{"type":"script","weight":1},"route-tags.chunk.2ee7e.esm.js":{"type":"script","weight":0.9},"route-tags.chunk.3ba37.css":{"type":"style","weight":0.9}}}